Tcl/__init__.py
Tcl/setup.py
Tcl-0.2.dist-info/METADATA
Tcl-0.2.dist-info/WHEEL
Tcl-0.2.dist-info/top_level.txt
Tcl-0.2.dist-info/RECORD
